openassetio_manager_bal/BasicAssetLibraryInterface.py
openassetio_manager_bal/__init__.py
openassetio_manager_bal/bal.py
openassetio_manager_bal-1.0.0a16.dist-info/LICENSE
openassetio_manager_bal-1.0.0a16.dist-info/METADATA
openassetio_manager_bal-1.0.0a16.dist-info/WHEEL
openassetio_manager_bal-1.0.0a16.dist-info/entry_points.txt
openassetio_manager_bal-1.0.0a16.dist-info/top_level.txt
openassetio_manager_bal-1.0.0a16.dist-info/RECORD
