Metadata-Version: 2.1
Name: openassetio-manager-bal
Version: 1.0.0a16
Summary: A contrived "asset management system" for OpenAssetIO integration test cases.
Author-email: Contributors to the OpenAssetIO project <openassetio-discussion@lists.aswf.io>
Project-URL: OpenAssetIO, https://github.com/OpenAssetIO/OpenAssetIO
Project-URL: Source, https://github.com/OpenAssetIO/OpenAssetIO-Manager-BAL
Project-URL: Issues, https://github.com/OpenAssetIO/OpenAssetIO-Manager-BAL/issues
Keywords: openassetio,manager
Classifier: Development Status :: 3 - Alpha
Classifier: Intended Audience :: Developers
Classifier: License :: OSI Approved :: Apache Software License
Classifier: Natural Language :: English
Classifier: Operating System :: MacOS
Classifier: Operating System :: Microsoft :: Windows
Classifier: Operating System :: POSIX :: Linux
Classifier: Programming Language :: Python :: 3
Requires-Python: >=3.7
License-File: LICENSE
Requires-Dist: openassetio >=1.0.0b2.rev0
Requires-Dist: openassetio-mediacreation >=1.0.0a7
